ringfit/__init__.py
ringfit/analysis_object.py
ringfit/centroids.py
ringfit/extraction.py
ringfit/fitting.py
ringfit-0.4.8.dist-info/METADATA
ringfit-0.4.8.dist-info/WHEEL
ringfit-0.4.8.dist-info/top_level.txt
ringfit-0.4.8.dist-info/RECORD
