Metadata-Version: 2.4
Name: ringfit
Version: 0.4.8
Requires-Dist: numpy
Requires-Dist: scipy
Requires-Dist: matplotlib
Requires-Dist: Pillow
Requires-Dist: ehtim
Dynamic: requires-dist
